git_stalk/__init__.py
git_stalk/stalk.py
tests/__init__.py
tests/test_user_existence.py
git_stalk-1.6.0.dist-info/LICENSE
git_stalk-1.6.0.dist-info/METADATA
git_stalk-1.6.0.dist-info/WHEEL
git_stalk-1.6.0.dist-info/entry_points.txt
git_stalk-1.6.0.dist-info/top_level.txt
git_stalk-1.6.0.dist-info/RECORD
