Metadata-Version: 2.1
Name: git-stalk
Version: 1.6.0
Summary: For stalkers like Daddu
Home-page: https://github.com/aashutoshrathi/git-stalk-cli
Author: Aashutosh Rathi
Author-email: aashutoshrathi@gmail.com
License: UNKNOWN
Platform: UNKNOWN
Classifier: Programming Language :: Python :: 3
Classifier: Programming Language :: Python :: 3.6
Classifier: Programming Language :: Python :: 3.7
Classifier: License :: OSI Approved :: MIT License
Classifier: Operating System :: OS Independent
Requires-Dist: requests
Requires-Dist: prettytable
Requires-Dist: python-dateutil
Requires-Dist: tox
Requires-Dist: docopt
